aurx/__init__.py
aurx/cli.py
aurx/interpreter.py
aurx-0.1.0.dist-info/licenses/LICENSE
aurx-0.1.0.dist-info/METADATA
aurx-0.1.0.dist-info/WHEEL
aurx-0.1.0.dist-info/entry_points.txt
aurx-0.1.0.dist-info/top_level.txt
aurx-0.1.0.dist-info/RECORD
